sphinxmixcrypto/__init__.py
sphinxmixcrypto/_metadata.py
sphinxmixcrypto/client.py
sphinxmixcrypto/crypto_primitives.py
sphinxmixcrypto/errors.py
sphinxmixcrypto/interfaces.py
sphinxmixcrypto/node.py
sphinxmixcrypto/padding.py
sphinxmixcrypto-0.0.4.dist-info/DESCRIPTION.rst
sphinxmixcrypto-0.0.4.dist-info/METADATA
sphinxmixcrypto-0.0.4.dist-info/RECORD
sphinxmixcrypto-0.0.4.dist-info/WHEEL
sphinxmixcrypto-0.0.4.dist-info/metadata.json
sphinxmixcrypto-0.0.4.dist-info/top_level.txt
