Metadata-Version: 2.0
Name: sphinxmixcrypto
Version: 0.0.4
Summary:     Sphinx mixnet crypto
Requires-Dist: PyNaCl (>=1.0.1)
Requires-Dist: attrs (>=16.3.0)
Requires-Dist: cryptography (>=1.5.2)
Requires-Dist: pyblake2 (>=0.9.3)
Requires-Dist: pycrypto (>=2.6.1)
Requires-Dist: pycryptodomex (>=3.4.3)
Requires-Dist: pylioness (==0.0.1)
Requires-Dist: zope.interface (>=4.3.2)
Provides-Extra: dev
Requires-Dist: codecov; extra == 'dev'
Requires-Dist: coverage; extra == 'dev'
Requires-Dist: coveralls; extra == 'dev'
Requires-Dist: hypothesis; extra == 'dev'
Requires-Dist: pep8; extra == 'dev'
Requires-Dist: pyflakes; extra == 'dev'
Requires-Dist: pytest; extra == 'dev'
Requires-Dist: setuptools (>=0.8.0); extra == 'dev'
Requires-Dist: tox; extra == 'dev'
Requires-Dist: wheel; extra == 'dev'
